MANIFEST.in
pyproject.toml
setup.py
cIA/cia.cpp
cIA/cia.pyx
pyIA/__init__.py
pyIA/actions.py
pyIA/agents.py
pyIA/arguments.py
pyIA/ia_planning.py
pyIA/mdptree.py
pyIA/paths.py
pyIA/simulator.py
pyIA/state_estimation.py
pyIA/maps/asl.pgm
pyIA/maps/asl.yaml
pyIA/maps/asl_graph.pickle
pyIA/maps/corridors.pgm
pyIA/maps/corridors.yaml
pyIA/maps/default.pgm
pyIA/maps/default.yaml
pyIA/scenarios/aslbusy.pickle
pyIA/scenarios/aslgates.pickle
pyIA/scenarios/aslgroups.pickle
pyIA/scenarios/aslguards.pickle
pyIA/scenarios/aslquiet.pickle
pyIA/scenarios/asltrap.pickle
pyIA/scenarios/irosasl1.pickle
pyIA/scenarios/irosasl2.pickle
pyIA/scenarios/irosasl3.pickle
pyIA/scenarios/irosasl4.pickle
pyIA/scenarios/irosasl5.pickle
pyIA/scenarios/irosasl6.pickle
pyIA/scenarios/irosasl_office_j1.pickle
pyIA/scenarios/irosasl_office_j2.pickle
pyIA/scenarios/irosasl_office_j3.pickle
pyIA/scenarios/irosasl_office_j4.pickle
pyIA/scenarios/irosasl_office_j5.pickle
pyIA/scenarios/irosasl_office_j6.pickle
pyIA/scenarios/irosunity_scene_map1.pickle
pyIA/scenarios/irosunity_scene_map2.pickle
pyIA/scenarios/irosunity_scene_map3.pickle
pyIA/scenarios/irosunity_scene_map4.pickle
pyIA/scenarios/irosunity_scene_map5.pickle
pyIA/scenarios/irosunity_scene_map6.pickle
pyIA/scenarios/none.pickle
pyIA/scenarios/officegroups.pickle
pyIA/scenarios/rlasl1.pickle
pyIA/scenarios/rlasl2.pickle
pyIA/scenarios/rlasl3.pickle
pyIA/scenarios/rlasl_office_j1.pickle
pyIA/scenarios/rlasl_office_j2.pickle
pyIA/scenarios/rlasl_office_j3.pickle
pyIA/scenarios/rlunity_scene_map1.pickle
pyIA/scenarios/rlunity_scene_map2.pickle
pyIA/scenarios/rlunity_scene_map3.pickle
pyIA/scenarios/scenarios.txt
pyIA/scenarios/toyempty1.pickle
pyIA/scenarios/unitytest.pickle
pyIAN.egg-info/PKG-INFO
pyIAN.egg-info/SOURCES.txt
pyIAN.egg-info/dependency_links.txt
pyIAN.egg-info/top_level.txt