Metadata-Version: 1.0
Name: pyIAN
Version: 0.0.3
Summary: Python library for IAN multibehavior planner
Home-page: UNKNOWN
Author: Daniel Dugas
Author-email: UNKNOWN
License: UNKNOWN
Platform: UNKNOWN
